ColorInfo/ColorInfo.py
ColorInfo/__init__.py
ColorInfo-2.2.0.dist-info/LICENSE
ColorInfo-2.2.0.dist-info/METADATA
ColorInfo-2.2.0.dist-info/WHEEL
ColorInfo-2.2.0.dist-info/top_level.txt
ColorInfo-2.2.0.dist-info/RECORD
