Metadata-Version: 2.1
Name: ColorInfo
Version: 2.2.0
Summary: ColorInfo 是一个使用Python3编写的简单的彩色日志工具，拥有简单、友好的语法,采用纯原始功能实现,无需依赖任何第三方模块
Home-page: https://gitee.com/liumou_site/ColorInfo
Author: 坐公交也用券
Author-email: liumou.site@qq.com
License: UNKNOWN
Platform: UNKNOWN
Classifier: Programming Language :: Python :: 3
Classifier: License :: OSI Approved :: MIT License
Classifier: Operating System :: OS Independent
Requires-Python: >=3.0
